{
    "text_block_list": [
        {
            "name": "Monólogo",
            "text": "Depois de um passeio com a Special<n>Week, eu a\nacompanho de volta ao<n>dormitório."
        },
        {
            "name": "Special Week",
            "text": "Hehe, hoje foi muito divertido!"
        },
        {
            "name": "Special Week",
            "text": "É diferente quando eu saio com você,<n>Treinador."
        },
        {
            "name": "Special Week",
            "text": "Não é como quando saio com a minha<n>mãe ou\ncom minhas amigas. Eu fico<n>até meio nervosa..."
        },
        {
            "name": "Special Week",
            "text": "Ah! Mas não de um jeito ruim!"
        },
        {
            "name": "Special Week",
            "text": "Acho que minha empolgação se<n>transforma em\nnervosismo... É difícil<n>de explicar...",
            "choice_data_list": [
                "Onde você costuma ir com a sua mãe?",
                "Onde você costuma ir com a sua mãe?",
                "Onde você costuma ir com suas amigas?",
                "Onde você costuma ir com suas amigas?"
            ]
        },
        {
            "name": "Special Week",
            "text": "Acho que minha empolgação se<n>transforma em\nnervosismo... É difícil<n>de explicar...",
            "choice_data_list": [
                "Onde você costuma ir com a sua mãe?",
                "Onde você costuma ir com a sua mãe?",
                "Onde você costuma ir com suas amigas?",
                "Onde você costuma ir com suas amigas?"
            ]
        },
        {
            "name": "Special Week",
            "text": "Com a minha mãe, a gente vai na<n>fazenda do\noutro lado da rua e ajuda<n>lá..."
        },
        {
            "name": "Special Week",
            "text": "E a gente entrega avisos da<n>comunidade pros\nidosos da<n>vizinhança."
        },
        {
            "name": "Special Week",
            "text": "Peraí... Isso conta como sair?"
        },
        {
            "name": "Special Week",
            "text": "Na verdade, conta sim! Sair não<n>precisa ser pra\nalgum lugar especial.<n>Só precisa ser divertido,\nhehe!"
        },
        {
            "name": "Special Week",
            "text": "Hmmm, a El me leva em restaurantes<n>com comida\nsuper apimentada às<n>vezes..."
        },
        {
            "name": "Special Week",
            "text": "E com a King, eu encaro desafios de<n>tigelas\ngigantes de ramen..."
        },
        {
            "name": "Special Week",
            "text": "Espera. Eu só como quando saio? Ai,<n>que\nvergonha..."
        }
    ]
}
