{
    "text_block_list": [
        {
            "name": "Monólogo",
            "text": "Mihono Bourbon vence, destruindo o<n>sonho da\nMatikanetannhauser de se<n>tornar campeã da\nTríplice Coroa."
        },
        {
            "name": "Monólogo",
            "text": "Otimista como sempre,<n>Matikanetannhauser quer\nusar o que<n>aprendeu na corrida de hoje para se\nsair melhor no Japanese Derby.",
            "color_text_info_list": [
                "Japanese Derby"
            ]
        },
        {
            "name": "Monólogo",
            "text": "Rice Shower, que também perdeu<n>hoje, está\nmotivada para o futuro<n>também, reconhecendo\nque ainda tem<n>um longo caminho a percorrer."
        },
        {
            "name": "Monólogo",
            "text": "Nosso ano clássico está longe de<n>terminar, e\nvamos continuar correndo<n>em direção ao\nJapanese Derby!"
        }
    ]
}
