{
    "text_block_list": [
        {
            "name": "Monólogo",
            "text": "No caminho de volta de um passeio<n>com a\nAdmire Vega..."
        },
        {
            "name": "???",
            "text": "Ayabeee!"
        },
        {
            "name": "Ines Fujin",
            "text": "Desculpe, desculpe! Minhas irmãs<n>gêmeas\nvieram correndo assim que<n>te viram, Ayabe!"
        },
        {
            "name": "Irmã Mais Nova da Ines A",
            "text": "Estamos a caminho do aquário!<n>Venha com a\ngente, Ayabe!"
        },
        {
            "name": "Irmã Mais Nova da Ines B",
            "text": "Por favor! Por favor! Pooor favooor<n>venha!"
        },
        {
            "name": "Ines Fujin",
            "text": "Ei, parem com isso! Eu disse para<n>não\nagarrarem a Ayabe!",
            "choice_data_list": [
                "O que você quer fazer?"
            ]
        },
        {
            "name": "Admire Vega",
            "text": "Você está perguntando para mim?<n>Bem, parece\nque elas não vão soltar..."
        },
        {
            "name": "Admire Vega",
            "text": "Então, acho que não tenho muita<n>escolha..."
        },
        {
            "name": "Monólogo",
            "text": "E assim, todos chegamos ao aquário.",
            "choice_data_list": [
                "As meninas parecem muito apegadas a você.",
                "As meninas parecem muito apegadas a você."
            ]
        },
        {
            "name": "Ines Fujin",
            "text": "Haha, elas estão mesmo! Na verdade,<n>da última\nvez que estiveram juntas..."
        },
        {
            "name": "Ines Fujin",
            "text": "Graças a Deus! Aqui estão vocês!<n>Desculpe, eu\ndesviei o olhar e—"
        },
        {
            "name": "Ines Fujin",
            "text": "Ah, Ayabe?"
        },
        {
            "name": "Admire Vega",
            "text": "Olha, ela chegou. Vou indo nessa,<n>então."
        },
        {
            "name": "Irmã Mais Nova da Ines A",
            "text": "Até logo, Ayabe! Conte-nos mais<n>sobre as\nestrelas na próxima vez!"
        },
        {
            "name": "Ines Fujin",
            "text": "Hã? Vocês estavam falando sobre<n>estrelas?"
        },
        {
            "name": "Irmã Mais Nova da Ines B",
            "text": "Sim, enquanto estávamos andando<n>por aí\nprocurando por você, a Ayabe<n>nos trouxe aqui!"
        },
        {
            "name": "Irmã Mais Nova da Ines B",
            "text": "Ela nos disse que você viria se<n>esperássemos\npor você!"
        },
        {
            "name": "Irmã Mais Nova da Ines A",
            "text": "Enquanto esperávamos, ela nos<n>contou um\nmonte de coisas sobre as<n>estrelas! ♪"
        },
        {
            "name": "Ines Fujin",
            "text": "Não é interessante?!",
            "choice_data_list": [
                "E agora elas não desgrudam dela."
            ]
        },
        {
            "name": "Irmã Mais Nova da Ines A",
            "text": "Ei, ei, Ayabe! Como se lê esta<n>palavra? Tem\ninsetos aqui?"
        },
        {
            "name": "Admire Vega",
            "text": "Não é um inseto. Diz \"polvo\"."
        },
        {
            "name": "Irmã Mais Nova da Ines B",
            "text": "Uau! Vem ver isso, Ayabe! Rápido! Os<n>peixes têm\ncores muito bonitas!"
        },
        {
            "name": "Admire Vega",
            "text": "Não precisa de pressa. Os peixes não<n>vão a lugar\nnenhum..."
        },
        {
            "name": "Ines Fujin",
            "text": "Como está o Omelete de Baleia que<n>você estava\nansiosa para provar?<n>Está gostoso?"
        },
        {
            "name": "Irmã Mais Nova da Ines A",
            "text": "Sim! É super delícia! ♪ Ah, você quer<n>um pouco\ntambém, Ayabe?"
        },
        {
            "name": "Admire Vega",
            "text": "Venha aqui primeiro... Você está com<n>ketchup em\nvolta da boca."
        },
        {
            "name": "Irmã Mais Nova da Ines B",
            "text": "O golfinho veio para cá! Uaaaaau! Ele<n>pulou tão\nalto!"
        },
        {
            "name": "Ines Fujin",
            "text": "...Ih, ficar parada aqui pode não ser a<n>melhor\nideia!"
        },
        {
            "name": "Admire Vega",
            "text": "...!"
        },
        {
            "name": "Monólogo",
            "text": "<i>TCHIBUM!</i>"
        },
        {
            "name": "Admire Vega",
            "text": "...Você está bem?"
        },
        {
            "name": "Irmã Mais Nova da Ines A",
            "text": "Obrigada, Ayabe! Ah não! Você ficou<n>encharcada!"
        },
        {
            "name": "Ines Fujin",
            "text": "Uaaaaah! Sinto muito! Venha aqui — eu<n>tenho uma\ntoalha que você pode<n>usar!"
        },
        {
            "name": "Ines Fujin",
            "text": "Obrigada por hoje, Ayabe! As<n>meninas se\ndivertiram muito! Faz<n>tempo que não as vejo\nficando<n>animadas assim!"
        },
        {
            "name": "Irmãs Mais Novas da Ines",
            "text": "Obrigada por vir, Ayabe! Vamos<n>brincar juntas de\nnovo em breve!"
        },
        {
            "name": "Admire Vega",
            "text": "...Heh."
        },
        {
            "name": "Admire Vega",
            "text": "Estou... exausta.",
            "choice_data_list": [
                "Mas você se divertiu, não foi?",
                "Mas você se divertiu, não foi?",
                "Elas são boas irmãs.",
                "Elas são boas irmãs."
            ]
        },
        {
            "name": "Admire Vega",
            "text": "Estou... exausta.",
            "choice_data_list": [
                "Mas você se divertiu, não foi?",
                "Mas você se divertiu, não foi?",
                "Elas são boas irmãs.",
                "Elas são boas irmãs."
            ]
        },
        {
            "name": "Admire Vega",
            "text": "Pode ser, mas mesmo assim..."
        },
        {
            "name": "Admire Vega",
            "text": "Quero dizer... acho que não foi de todo<n>ruim."
        },
        {
            "name": "Admire Vega",
            "text": "É."
        },
        {
            "name": "Admire Vega",
            "text": "Elas realmente são..."
        }
    ]
}
