{
    "text_block_list": [
        {
            "name": "Monólogo",
            "text": "As I pass by the gym, I see Satono<n>Diamond and\nKitasan Black arguing<n>about something."
        },
        {
            "name": "Kitasan Black",
            "text": "Don't do it, Dia! It's not safe!"
        },
        {
            "name": "Satono Diamond",
            "text": "There's nothing to fret about! I'll be<n>fine!",
            "choice_data_list": [
                "What seems to be the problem?"
            ]
        },
        {
            "name": "Kitasan Black",
            "text": "Oh, thank goodness you're here!<n>Please, you\nhave to help me stop her!"
        },
        {
            "name": "Monólogo",
            "text": "They tell me how the gym's treadmill<n>has a\n\"lunatic\" setting that's so<n>difficult, nobody has\nmanaged to<n>conquer it."
        },
        {
            "name": "Monólogo",
            "text": "Satono Diamond, brimming with<n>unbridled\ncuriosity, is apparently<n>determined to be the first\none to do it."
        },
        {
            "name": "Kitasan Black",
            "text": "If no Umamusume has ever been able<n>to run on\nthat speed, that must mean<n>it's extremely\ndangerous!"
        },
        {
            "name": "Satono Diamond",
            "text": "Kita, please don't try to stop me. You<n>know how I\nam."
        },
        {
            "name": "Satono Diamond",
            "text": "It's no fun to draw conclusions on<n>something\nbefore trying it out."
        },
        {
            "name": "Satono Diamond",
            "text": "I won't fail this endeavor! I swear it!",
            "choice_data_list": [
                "Well, give it a shot!",
                "Let's see how fast it really is first."
            ]
        },
        {
            "name": "Satono Diamond",
            "text": "Hehe, thank you. I appreciate your<n>words of\nencouragement."
        },
        {
            "name": "Satono Diamond",
            "text": "I know I can do it. Just watch and<n>see."
        },
        {
            "name": "Monólogo",
            "text": "She sets the speed to lunatic, and the<n>machine\nstarts emitting a high-pitched<n>zipping noise as the\nbelt starts<n>spinning at blinding speed!"
        },
        {
            "name": "Kitasan Black",
            "text": "Wh-whoa!"
        },
        {
            "name": "Satono Diamond",
            "text": "So this is how fast it is... I can't wait<n>to try this!\nHere I go!"
        },
        {
            "name": "Kitasan Black",
            "text": "Dia, nooo! Don't do it! It's too<n>dangerous!"
        },
        {
            "name": "Monólogo",
            "text": "We somehow manage to stop the<n>\noverenthusiastic Satono Diamond<n>before she\ndoes something reckless."
        },
        {
            "name": "Satono Diamond",
            "text": "Hmph... Fine. Seeing as a trainer is<n>the one\nsuggesting caution, I suppose<n>this does require\nprior investigation."
        },
        {
            "name": "Monólogo",
            "text": "She sets the speed to lunatic, and the<n>machine\nstarts emitting a high-pitched<n>zipping noise as the\nbelt starts<n>spinning at blinding speed!"
        },
        {
            "name": "Kitasan Black",
            "text": "I told you, Dia! It's too dangerous!<n>You can't\nstart running at that speed<n>without any\npreparation!"
        },
        {
            "name": "Satono Diamond",
            "text": "Yes, you're right... Then I'll simply<n>have to work\nmy way up to it!"
        },
        {
            "name": "Satono Diamond",
            "text": "I'll start with the exercise bike on the<n>highest\n\"catastrophe\" difficulty!"
        },
        {
            "name": "Kitasan Black",
            "text": "N-noooo! No one's been able to do<n>that one\neither!"
        },
        {
            "name": "Monólogo",
            "text": "We somehow manage to stop the<n>\noverenthusiastic Satono Diamond<n>before she\ndoes something reckless."
        }
    ]
}
