{
    "text_block_list": [
        {
            "name": "Haru Urara",
            "text": "Urara, la la la! ♪ Como será que vai<n>ser o treino de\nhoje? ♪"
        },
        {
            "name": "Moça Fazendo Compras",
            "text": "Ah, Urara! Bem na hora! Se importa<n>de\nexperimentar minha bala de<n>cenoura?"
        },
        {
            "name": "Haru Urara",
            "text": "Bala?! Sério? Sério?! É claro que sim!"
        },
        {
            "name": "Haru Urara",
            "text": "Mmm! Tão gostosa! Essas vão voar<n>das\nprateleiras! Eu garanto!"
        },
        {
            "name": "Moça Fazendo Compras",
            "text": "Hoho, que bom ouvir isso! Você traz<n>um sorriso ao\nmeu rosto, Urara."
        },
        {
            "name": "Haru Urara",
            "text": "Hihi, é sério? Então eu provo o<n>quanto você quiser\nque eu prove!"
        },
        {
            "name": "Moça Fazendo Compras",
            "text": "Ah, que doçura a sua! Aqui, deixe-me<n>ir buscar\nmais."
        },
        {
            "name": "Haru Urara",
            "text": "Eba! Eu vou fazer o Treinador provar<n>um pouco\ntambém!"
        },
        {
            "name": "Haru Urara",
            "text": "...Ah, espera! AHH! O treino tá prestes<n>a começar!"
        },
        {
            "name": "Haru Urara",
            "text": "O que que eu faço? Eu não posso<n>deixar as balas\npra trás, mas..."
        },
        {
            "name": "Haru Urara",
            "text": "Ah, já sei! Eu levo um pouco pro<n>Treinador\ndepois! Eu sou tão esperta!"
        },
        {
            "name": "Haru Urara",
            "text": "Hehehehe! ♪ Hora da bala! ♪ Hora da<n>bala! ♪"
        },
        {
            "name": "Monólogo",
            "text": "O coração da Haru Urara é roubado<n>pelas balas, e\ncomo resultado, ela<n>mata o treino de hoje."
        }
    ]
}
