{
    "text_block_list": [
        {
            "name": "Monólogo",
            "text": "No acampamento de verão,<n>Maruzensky e eu trabalhamos duro<n>para melhorar sua corrida ainda mais.<n>Maruzensky está com ânimo total<n>enquanto o sol nasce no último dia."
        },
        {
            "name": "Maruzensky",
            "text": "Bom dia, Treinador. Vamos lá!<n>Precisamos que nosso último dia de<n>treino seja nota dez!"
        },
        {
            "name": "Maruzensky",
            "text": "Bom dia, Treinadora. Vamos lá!<n>Precisamos que nosso último dia de<n>treino seja nota dez!"
        },
        {
            "name": "Maruzensky",
            "text": "É agora, sabe? Então vamos dar o<n>gás e mandar ver!"
        },
        {
            "name": "Monólogo",
            "text": "Uma Maruzensky revigorada encara<n>o último dia de treino comigo."
        },
        {
            "name": "Maruzensky",
            "text": "Ufa... Valeu, Treinador! Hehe, parece<n>que nós dois suamos a camisa.",
            "choice_data_list": [
                "Mas nós conseguimos!",
                "Mas nós conseguimos!"
            ]
        },
        {
            "name": "Maruzensky",
            "text": "Ufa... Valeu, Treinadora! Hehe, parece<n>que nós duas suamos a camisa.",
            "choice_data_list": [
                "Mas nós conseguimos!",
                "Mas nós conseguimos!"
            ]
        },
        {
            "name": "Maruzensky",
            "text": "É! Estou exausta, mas tipo, elétrica ao<n>mesmo tempo. Eu me sinto uma uva!"
        },
        {
            "name": "Maruzensky",
            "text": "Depois de todo esse treino, mal<n>posso esperar pela minha próxima<n>corrida. Hehe, acho que você vai<n>curtir."
        },
        {
            "name": "Maruzensky",
            "text": "Mas ei... Você está bem? Não está<n>cansado de ficar sob o sol por tanto<n>tempo?",
            "choice_data_list": [
                "Vou ficar bem quando descansar."
            ]
        },
        {
            "name": "Maruzensky",
            "text": "Mas ei... Você está bem? Não está<n>cansada de ficar sob o sol por tanto<n>tempo?",
            "choice_data_list": [
                "Vou ficar bem quando descansar."
            ]
        },
        {
            "name": "Maruzensky",
            "text": "Tem certeza? Não vá se<n>sobrecarregar, tá legal?"
        },
        {
            "name": "Maruzensky",
            "text": "Bem, eu vou voltar e me lavar. É<n>importante descansar bastante<n>depois de um treino pesado!"
        },
        {
            "name": "Monólogo",
            "text": "Volto para o meu quarto e tomo um<n>banho relaxante. Depois, saio para<n>tomar um pouco de ar fresco da<n>noite..."
        },
        {
            "name": "Maruzensky",
            "text": "Eu sei o que o Treinador disse, mas<n>tivemos um dia bem cansativo.<n>Espero não estar sendo egoísta..."
        },
        {
            "name": "Maruzensky",
            "text": "Mas...",
            "choice_data_list": [
                "O que foi?",
                "O que foi?"
            ]
        },
        {
            "name": "Maruzensky",
            "text": "Ah, Treinador..."
        },
        {
            "name": "Maruzensky",
            "text": "Ah, Treinadora..."
        },
        {
            "name": "Maruzensky",
            "text": "Er... ouvi de outra aluna que está<n>rolando um festival no santuário aqui<n>perto."
        },
        {
            "name": "Maruzensky",
            "text": "E..."
        },
        {
            "name": "Maruzensky",
            "text": "Quer saber, eu vou perguntar!"
        },
        {
            "name": "Maruzensky",
            "text": "Quer jantar nas barraquinhas de<n>comida lá?!"
        },
        {
            "name": "Maruzensky",
            "text": "Dizem que vai ter barracas de jogos<n>também, e vai ter a dança do festival!<n>Aposto que a gente ia se divertir<n>muito juntos!",
            "choice_data_list": [
                "Parece ótimo! Vamos nessa!",
                "Parece ótimo! Vamos nessa!"
            ]
        },
        {
            "name": "Maruzensky",
            "text": "Ah, maravilhoso!"
        },
        {
            "name": "Maruzensky",
            "text": "Certo! Com isso decidido, eu vou<n>dançar até cansar na festa!"
        },
        {
            "name": "Maruzensky",
            "text": "Vem, Treinador! Por aqui!"
        },
        {
            "name": "Maruzensky",
            "text": "Vem, Treinadora! Por aqui!"
        },
        {
            "name": "Maruzensky",
            "text": "Uauuu! Está <i>tão</i> cheio, né? Eu<n>quero muito dar uma olhada em uma<n>barraquinha específica, mas não<n>estou vendo ela em lugar nenhum.",
            "choice_data_list": [
                "Hm? Que barraquinha?"
            ]
        },
        {
            "name": "Maruzensky",
            "text": "Hehehe. ♪ Não é uma barraquinha<n>qualquer. Preparado?"
        },
        {
            "name": "Maruzensky",
            "text": "É uma loja de sobremesas, e é o<n>suprassumo!",
            "choice_data_list": [
                "(O suprassumo?!)"
            ]
        },
        {
            "name": "Maruzensky",
            "text": "Todas as alunas estão dizendo que o<n>Parfait Deluxe de Torre de Cenoura,<n>edição de verão, é um estouro total."
        },
        {
            "name": "Maruzensky",
            "text": "Estou com medo de que acabem logo<n>por serem tão populares, mas<n>devíamos deixar a sobremesa para<n>depois."
        },
        {
            "name": "Maruzensky",
            "text": "Você sabe o que temos que fazer<n>primeiro."
        },
        {
            "name": "Monólogo",
            "text": "<i>Dã, dã, dã, ba, ba, bum. ♪</i>"
        },
        {
            "name": "Maruzensky",
            "text": "Ali! A dança! Ah, isso me traz<n>recordações... Minha família sempre<n>dançava quando eu era pequena.",
            "choice_data_list": [
                "Vamos lá ver!"
            ]
        },
        {
            "name": "Maruzensky",
            "text": "É, vamos lá! É hora de entrar no ritmo!"
        },
        {
            "name": "Monólogo",
            "text": "Nós nos juntamos à dança, e<n>Maruzensky se apresenta<n>lindamente. Todos ali estão<n>contagiados pela animação."
        },
        {
            "name": "Maruzensky",
            "text": "U-hu! Ainda não acabou! Vamos lá,<n>Treinador! Tá no pique?"
        },
        {
            "name": "Maruzensky",
            "text": "U-hu! Ainda não acabou! Vamos lá,<n>Treinadora! Tá no pique?"
        },
        {
            "name": "Monólogo",
            "text": "Conforme o evento esquenta ainda<n>mais, a dança fica grande demais<n>para ser contida."
        },
        {
            "name": "Maruzensky",
            "text": "Ahhh! Que diversão! Você dança<n>muito bem, Treinador!",
            "choice_data_list": [
                "Essa dança foi intensa...",
                "Essa dança foi intensa..."
            ]
        },
        {
            "name": "Maruzensky",
            "text": "Ahhh! Que diversão! Você dança<n>muito bem, Treinadora!",
            "choice_data_list": [
                "Essa dança foi intensa...",
                "Essa dança foi intensa..."
            ]
        },
        {
            "name": "Maruzensky",
            "text": "Foi mesmo! Estava todo mundo se<n>acabando de dançar! Eu me<n>empolguei tanto que acabei indo parar<n>no palco principal. ♪"
        },
        {
            "name": "Maruzensky",
            "text": "Meu corpo todo vibrava por estar ao<n>lado dos tambores taiko! Foi<n>simplesmente o máximo!"
        },
        {
            "name": "Maruzensky",
            "text": "Minha mãe sempre dizia: \"Quando<n>você estiver num palco grande, é<n>hora de cair na dança.\" Hehe, acho<n>que tal mãe, tal filha.",
            "choice_data_list": [
                "Ah, então você herdou isso dela...",
                "Ah, então você herdou isso dela..."
            ]
        },
        {
            "name": "Maruzensky",
            "text": "Hm? Você disse alguma coisa?"
        },
        {
            "name": "Maruzensky",
            "text": "Ah, é mesmo! Precisamos ir buscar<n>nossa sobremesa!"
        },
        {
            "name": "Maruzensky",
            "text": "Vamos encontrar esse Parfait Deluxe<n>de Torre de Cenoura!"
        },
        {
            "name": "Monólogo",
            "text": "Pegamos nossos parfaits de cenoura<n>e aproveitamos as outras barracas.<n>Depois de ver tudo o que havia para<n>ver, é hora de voltar."
        },
        {
            "name": "Maruzensky",
            "text": "Aquele parfait estava divino! Tinha<n>até sorvete entre os macarons... Meu<n>coração está tão cheio quanto meu<n>estômago. ♪"
        },
        {
            "name": "Maruzensky",
            "text": "Eu pude correr pela orla, dançar no<n>festival e comer uma sobremesa<n>irada..."
        },
        {
            "name": "Maruzensky",
            "text": "Eu nunca imaginei que passaria<n>momentos tão bons com alguém."
        },
        {
            "name": "Maruzensky",
            "text": "Hehe, foi <i>muito</i> divertido. Promete<n>que podemos repetir a dose qualquer<n>hora?",
            "choice_data_list": [
                "Claro! Eu adoraria."
            ]
        },
        {
            "name": "Maruzensky",
            "text": "Tem certeza de que não precisa<n>pensar melhor?"
        },
        {
            "name": "Maruzensky",
            "text": "Tem certeza de que não precisa<n>pensar melhor?"
        },
        {
            "name": "Maruzensky",
            "text": "Se você disser sim para tudo, quem<n>sabe onde meus caprichos vão te<n>levar da próxima vez?",
            "choice_data_list": [
                "O que quer que seja, pode vir!",
                "O que quer que seja, pode vir!"
            ]
        },
        {
            "name": "Maruzensky",
            "text": "Hehe, por favor, eu sei que você está<n>cansado... Mas é isso aí! Devíamos<n>planejar nosso próximo passeio!"
        },
        {
            "name": "Maruzensky",
            "text": "...É muito estranho. Sinto que posso<n>ser eu mesma com você, ainda mais<n>do que quando estou sozinha."
        },
        {
            "name": "Maruzensky",
            "text": "...É muito estranho. Sinto que posso<n>ser eu mesma com você, ainda mais<n>do que quando estou sozinha."
        },
        {
            "name": "Maruzensky",
            "text": "Sinto que posso ir a qualquer lugar,<n>correr o quanto for — qualquer coisa. É<n>assim que você me faz sentir,<n>Treinador."
        },
        {
            "name": "Maruzensky",
            "text": "Sinto que posso ir a qualquer lugar,<n>correr o quanto for — qualquer coisa. É<n>assim que você me faz sentir,<n>Treinadora."
        },
        {
            "name": "Maruzensky",
            "text": "Eu não sei como você faz isso... Você<n>é realmente uma pessoa especial!",
            "choice_data_list": [
                "Você também é muito especial."
            ]
        },
        {
            "name": "Maruzensky",
            "text": "Eu não sei como você faz isso... Você<n>é realmente uma pessoa especial!",
            "choice_data_list": [
                "Você também é muito especial."
            ]
        },
        {
            "name": "Maruzensky",
            "text": "Uau! Acho que formamos uma bela<n>dupla, hein? ♪"
        },
        {
            "name": "Maruzensky",
            "text": "É meio embaraçoso dizer isso, mas...<n>espero que a gente continue<n>compartilhando muito mais diversão."
        },
        {
            "name": "Maruzensky",
            "text": "Uma corredora e seu Treinador — os<n>melhores parceiros! Um brinde a nós!"
        },
        {
            "name": "Maruzensky",
            "text": "Uma corredora e sua Treinadora — as<n>melhores parceiras! Um brinde a nós!"
        }
    ]
}
