{
    "text_block_list": [
        {
            "name": "King Halo",
            "text": "<i>Arf... Uf... Uf...</i>"
        },
        {
            "name": "King Halo",
            "text": "Não... Eu não posso parar aqui... Não<n>posso!"
        },
        {
            "name": "King Halo",
            "text": "Eu sou... de primeira classe..."
        },
        {
            "name": "Espectador Animado",
            "text": "Cara, essa corrida foi incrível!<n>Finalmente\nconsegui ver a Seiun Sky<n>e a Special Week!"
        },
        {
            "name": "Espectador Animado",
            "text": "Elas foram sensacionais!"
        },
        {
            "name": "Espectador Inquieto",
            "text": "Sim! Aposto que elas vão para o<n>Tenno Sho de\nprimavera, não acha?<n>Ou quem sabe até as\nveremos na<n>Arima Kinen!"
        },
        {
            "name": "Espectador Inquieto",
            "text": "De qualquer forma, estou muito<n>ansioso para ver\no que elas farão no<n>ano que vem! As duas com\ncerteza<n>têm minha torcida!"
        },
        {
            "name": "King Halo",
            "text": "..."
        },
        {
            "name": "King Halo",
            "text": "...Eu sou tão idiota."
        },
        {
            "name": "King Halo",
            "text": "Nem uma única pessoa está olhando<n>para mim."
        },
        {
            "name": "King Halo",
            "text": "..."
        },
        {
            "name": "King Halo",
            "text": "...Ei, Treinador."
        },
        {
            "name": "King Halo",
            "text": "Talvez eu estivesse errada. Talvez eu<n>não\ndevesse ter tentado."
        },
        {
            "name": "King Halo",
            "text": "Que vergonha...",
            "choice_data_list": [
                "Você não é uma vergonha."
            ]
        },
        {
            "name": "King Halo",
            "text": "M-Mas..."
        },
        {
            "name": "King Halo",
            "text": "No fim das contas, a minha mãe<n>estava certa."
        },
        {
            "name": "King Halo",
            "text": "Eu não consegui assumir o palco<n>principal. Não\ncheguei nem perto."
        },
        {
            "name": "King Halo",
            "text": "Não sou de primeira classe nem um<n>pouco...",
            "choice_data_list": [
                "Você é a King Halo, a Umamusume de primeira\nclasse!",
                "Você é a King Halo, a Umamusume de primeira\nclasse!"
            ]
        },
        {
            "name": "King Halo",
            "text": "Pare com isso!"
        },
        {
            "name": "King Halo",
            "text": "Não seja teimoso e olhe para a<n>realidade! Eu... Eu\nnão sou..."
        },
        {
            "name": "Kawakami Princess",
            "text": "King!"
        },
        {
            "name": "King Halo",
            "text": "...K-Kawakami? O que você está<n>fazendo aqui?"
        },
        {
            "name": "Kawakami Princess",
            "text": "Eu vim te apoiar! Você foi<n>simplesmente\nmaravilhosa lá!"
        },
        {
            "name": "Kawakami Princess",
            "text": "Suas passadas poderosas, suas<n>explosões de\nvelocidade... E acima de<n>tudo..."
        },
        {
            "name": "Kawakami Princess",
            "text": "Como você continua correndo com<n>essa postura\nlinda, não importa o que<n>aconteça! Eu\nsimplesmente amo ver<n>você correr!"
        },
        {
            "name": "King Halo",
            "text": "...K-Kawakami."
        },
        {
            "name": "Umamusume com Olhos de Gato",
            "text": "King! Bom trabalho lá fora! Você<n>realmente\ncompletou o circuito da<n>Tríplice Coroa!"
        },
        {
            "name": "Umamusume de Cabelo Curto",
            "text": "Você foi demais! Eu vou dar o meu<n>melhor para\npoder correr na Tríplice<n>Coroa algum dia também!"
        },
        {
            "name": "King Halo",
            "text": "Vocês todas me viram...",
            "choice_data_list": [
                "Afinal, as pessoas estavam olhando para você.",
                "Afinal, as pessoas estavam olhando para você."
            ]
        },
        {
            "name": "King Halo",
            "text": "..."
        },
        {
            "name": "",
            "text": "Mesmo com essa derrota, os olhos<n>ainda estão\nvoltados para a King<n>Halo.",
            "choice_data_list": [
                "Eu sei porque estive te observando o tempo todo.",
                "Eu sei porque estive te observando o tempo todo."
            ]
        },
        {
            "name": "",
            "text": "Não importa o quanto as coisas<n>possam ser\nfrustrantes, não importa<n>o quanto as pessoas\npossam ficar<n>chocadas com ela..."
        },
        {
            "name": "",
            "text": "Mesmo que suas conquistas não<n>satisfaçam sua\nmãe...",
            "choice_data_list": [
                "Você é uma Umamusume de primeira classe.",
                "Você é uma Umamusume de primeira classe."
            ]
        },
        {
            "name": "King Halo",
            "text": "..."
        },
        {
            "name": "",
            "text": "Mesmo que a vida lance sobre ela<n>inúmeros\nmomentos de partir o<n>coração, ela se erguerá e\nseguirá em<n>frente. Ela é uma Umamusume tenaz\nque merece ser admirada."
        },
        {
            "name": "",
            "text": "Seu talento e charme são<n>completamente\ndiferentes dos de sua<n>mãe. É isso que a torna\núnica."
        },
        {
            "name": "King Halo",
            "text": "Céus... Você está zombando de mim<n>ao continuar\nrepetindo isso?",
            "choice_data_list": [
                "Vou dizer isso de novo e de novo—você é de\nprimeira classe.",
                "Vou dizer isso de novo e de novo—você é de\nprimeira classe."
            ]
        },
        {
            "name": "King Halo",
            "text": "Sinceramente! Eu não aguento você!",
            "choice_data_list": [
                "(Não consigo evitar... Você também me encantou.)",
                "(Não consigo evitar... Você também me encantou.)"
            ]
        },
        {
            "name": "King Halo",
            "text": "..."
        },
        {
            "name": "King Halo",
            "text": "...Idiota."
        },
        {
            "name": "King Halo",
            "text": "Você é muito idiota! Em momentos<n>como esse, era\npara você me dar um<n>sermão!"
        },
        {
            "name": "King Halo",
            "text": "Em vez disso, você é apenas<n>cabeça-dura,\nteimoso e desajeitado."
        },
        {
            "name": "King Halo",
            "text": "E, acima de tudo, você é muito<n>tolerante!"
        },
        {
            "name": "King Halo",
            "text": "Sério... Não é nem um pouco<n>elegante..."
        },
        {
            "name": "King Halo",
            "text": "Por que... Por que nós dois somos tão<n>tolos?"
        },
        {
            "name": "",
            "text": "Eu ofereço meu ombro a ela até que<n>suas\nlágrimas parem."
        },
        {
            "name": "King Halo",
            "text": "...Ei, Treinador.",
            "choice_data_list": [
                "O que foi?"
            ]
        },
        {
            "name": "King Halo",
            "text": "Antes do Kikuka Sho, você estava<n>tentando me\ndizer alguma coisa, não<n>estava?"
        },
        {
            "name": "King Halo",
            "text": "...Bem, pode falar agora."
        },
        {
            "name": "",
            "text": "Mas ela não é igual à sua mãe. Há<n>lugares\ndiferentes onde o potencial<n>dela pode brilhar."
        },
        {
            "name": "King Halo",
            "text": "Estou pronta para ouvir."
        },
        {
            "name": "",
            "text": "Ela me olha intensamente,<n>esperando.",
            "choice_data_list": [
                "Pare de tentar chamar a atenção da sua mãe."
            ]
        },
        {
            "name": "King Halo",
            "text": "Hã?"
        },
        {
            "name": "King Halo",
            "text": "É <i>com isso</i> que você quer que eu<n>pare?"
        },
        {
            "name": "King Halo",
            "text": "Você não vai me dizer para parar de<n>correr longas\ndistâncias?"
        },
        {
            "name": "King Halo",
            "text": "Não vai me dizer para parar de correr<n>em corridas\nque eu não posso vencer<n>e focar naquilo em que\nsou boa?",
            "choice_data_list": [
                "Não. Eu quero que você seja de primeira classe\ndo seu próprio jeito."
            ]
        },
        {
            "name": "King Halo",
            "text": "Do meu próprio jeito..."
        },
        {
            "name": "",
            "text": "A King Halo não deveria estar<n>tentando seguir os\npassos de outra<n>pessoa, e não deveria estar\ncorrendo<n>atrás da aprovação de ninguém."
        },
        {
            "name": "King Halo",
            "text": "Tem certeza? Não tem problema<n>mesmo eu fazer\nas coisas do jeito<n>que eu quero?",
            "choice_data_list": [
                "Com certeza. Siga o seu próprio caminho.",
                "Com certeza. Siga o seu próprio caminho."
            ]
        },
        {
            "name": "",
            "text": "O caminho dela não deveria ser<n>influenciado por\nsua mãe ou por<n>qualquer outra pessoa."
        },
        {
            "name": "King Halo",
            "text": "Eu não deveria ser de primeira classe<n>pelos\noutros. Eu deveria ser de<n>primeira classe por mim\nmesma..."
        },
        {
            "name": "King Halo",
            "text": "Hehe, você está certo."
        },
        {
            "name": "King Halo",
            "text": "Eu gosto de como isso soa."
        }
    ]
}
