{
    "text_block_list": [
        {
            "name": "Monólogo",
            "text": "Durante uma reunião com a Mejiro<n>Bright..."
        },
        {
            "name": "Mejiro Bright",
            "text": "*Zzz... Zzz... Zzz...* Mngh..."
        },
        {
            "name": "Mejiro Bright",
            "text": "...Bem, bom dia para você,<n>passarinho. E olá para\nvocê,<n>coelhinho. Saudações a você também,\nesquilo fofo. ♪ Teehee..."
        },
        {
            "name": "Mejiro Bright",
            "text": "...Oh?"
        },
        {
            "name": "Mejiro Bright",
            "text": "Perdoe-me, mas você por acaso viu<n>para onde\nforam todas as criaturas<n>do bosque? O recital da\nfloresta está<n>prestes a começar, e nós\nensaiamos<n>tanto..."
        },
        {
            "name": "Mejiro Bright",
            "text": "...Treinador? Você não pode fazer sua<n>parte sem\no seu pandeiro..."
        },
        {
            "name": "Monólogo",
            "text": "A Mejiro Bright parece tão privada<n>de sono que\nnão consegue mais<n>distinguir o sonho da\nrealidade..."
        }
    ]
}
